cavotf/__init__.py
cavotf/__main__.py
cavotf/cli.py
cavotf/config.py
cavotf/dftb.py
cavotf/dynamics.py
cavotf/geometry.py
cavotf/hpc.py
cavotf/server_DFTB.py
cavotf/workflow.py
cavotf/resources/__init__.py
cavotf/resources/DFTB_clean/__init__.py
cavotf/resources/DFTB_clean/cavityDFTB.slurm
cavotf/resources/DFTB_clean/client_DFTB.py
cavotf/resources/DFTB_clean/client_DFTB_extend.py
cavotf/resources/DFTB_clean/dftb.py
cavotf/resources/DFTB_clean/funcLM.py
cavotf/resources/DFTB_clean/get_mu.py
cavotf/resources/DFTB_clean/muDFTB.slurm
cavotf-0.1.7.12.25.dist-info/METADATA
cavotf-0.1.7.12.25.dist-info/WHEEL
cavotf-0.1.7.12.25.dist-info/entry_points.txt
cavotf-0.1.7.12.25.dist-info/top_level.txt
cavotf-0.1.7.12.25.dist-info/RECORD
