Metadata-Version: 2.4
Name: cavotf
Version: 0.1.7.12.25
Summary: cavOTF.py Package
Author: Sachith Wickramasinghe, Amir H. Amini, Arkajit Mandal
License: MIT
Requires-Python: >=3.9
Requires-Dist: numpy
Requires-Dist: scipy
Requires-Dist: ase
